cuvis_il/__init__.py
cuvis_il/_cuvis_pyil.pyd
cuvis_il/cuvis_il.py
cuvis_il-3.5.0.dist-info/licenses/LICENSE
cuvis_il-3.5.0.dist-info/METADATA
cuvis_il-3.5.0.dist-info/WHEEL
cuvis_il-3.5.0.dist-info/top_level.txt
cuvis_il-3.5.0.dist-info/RECORD
