Metadata-Version: 2.4
Name: cuvis_il
Version: 3.5.0
Summary: Compiled Python Bindings for the CUVIS SDK.
Author-email: "Cubert GmbH, Ulm, Germany" <sdk@cubert-gmbh.com>
License-Expression: Apache-2.0
Project-URL: Homepage, https://www.cubert-hyperspectral.com/
Project-URL: Repository, https://github.com/cubert-hyperspectral/cuvis.pyil
Project-URL: Documentation, https://cubert-hyperspectral.github.io/cuvis.doc/
Project-URL: Changelog, https://github.com/cubert-hyperspectral/cuvis.pyil/releases
Project-URL: Issues, https://github.com/cubert-hyperspectral/cuvis.pyil/issues
Classifier: Intended Audience :: Developers
Classifier: Programming Language :: Python :: 3
Classifier: Programming Language :: Python :: 3.9
Classifier: Programming Language :: Python :: 3.10
Classifier: Programming Language :: Python :: 3.11
Classifier: Programming Language :: Python :: 3.12
Classifier: Programming Language :: Python :: 3.13
Classifier: Programming Language :: Python :: 3.14
Classifier: Topic :: Scientific/Engineering :: Image Processing
Requires-Python: >=3.9
License-File: LICENSE
Requires-Dist: numpy>=2.0.0; python_version >= "3.13"
Requires-Dist: numpy>=1.26.0; python_version >= "3.12"
Requires-Dist: numpy>=1.23.0; python_version >= "3.11"
Requires-Dist: numpy>=1.22.0; python_version >= "3.9"
Dynamic: license-file
